odoo/addons/analytic_mixin_analytic_account/README.rst
odoo/addons/analytic_mixin_analytic_account/__init__.py
odoo/addons/analytic_mixin_analytic_account/__manifest__.py
odoo/addons/analytic_mixin_analytic_account/i18n/analytic_mixin_analytic_account.pot
odoo/addons/analytic_mixin_analytic_account/i18n/eu_ES.po
odoo/addons/analytic_mixin_analytic_account/i18n/it.po
odoo/addons/analytic_mixin_analytic_account/i18n/ja.po
odoo/addons/analytic_mixin_analytic_account/models/__init__.py
odoo/addons/analytic_mixin_analytic_account/models/analytic_mixin.py
odoo/addons/analytic_mixin_analytic_account/readme/CONTRIBUTORS.rst
odoo/addons/analytic_mixin_analytic_account/readme/DESCRIPTION.rst
odoo/addons/analytic_mixin_analytic_account/static/description/icon.png
odoo/addons/analytic_mixin_analytic_account/static/description/index.html
odoo/addons/analytic_mixin_analytic_account/tests/__init__.py
odoo/addons/analytic_mixin_analytic_account/tests/test_analytic_mixin_analytic_account.py
odoo_addon_analytic_mixin_analytic_account-16.0.1.0.0.5.dist-info/METADATA
odoo_addon_analytic_mixin_analytic_account-16.0.1.0.0.5.dist-info/WHEEL
odoo_addon_analytic_mixin_analytic_account-16.0.1.0.0.5.dist-info/top_level.txt
odoo_addon_analytic_mixin_analytic_account-16.0.1.0.0.5.dist-info/RECORD
